pygsound-0.3.dist-info/RECORD
pygsound-0.3.dist-info/WHEEL
pygsound-0.3.dist-info/top_level.txt
pygsound-0.3.dist-info/LICENSE.txt
pygsound-0.3.dist-info/METADATA
pygsound/__init__.py
pygsound/pygsound.pypy37-pp73-darwin.so
pygsound/.dylibs/libfftw3f.3.dylib
pygsound/.dylibs/libfftw3_threads.3.dylib
pygsound/.dylibs/libfftw3.3.dylib
pygsound/.dylibs/libgcc_s.1.dylib
