Metadata-Version: 2.1
Name: pygsound
Version: 0.3
Summary: A room impulse response simulator using for geometric sound propagation
Author: Zhenyu Tang, Carl Schissler, Dinesh Manocha
Author-email: zhy@umd.edu
License: UNKNOWN
Platform: UNKNOWN
License-File: LICENSE.txt
